MANIFEST.in
README.rst
os_virtual_interfacesv2_python_novaclient_ext.py
setup.py
os_virtual_interfacesv2_python_novaclient_ext.egg-info/PKG-INFO
os_virtual_interfacesv2_python_novaclient_ext.egg-info/SOURCES.txt
os_virtual_interfacesv2_python_novaclient_ext.egg-info/dependency_links.txt
os_virtual_interfacesv2_python_novaclient_ext.egg-info/pbr.json
os_virtual_interfacesv2_python_novaclient_ext.egg-info/requires.txt
os_virtual_interfacesv2_python_novaclient_ext.egg-info/top_level.txt