Metadata-Version: 1.1
Name: os-virtual-interfacesv2-python-novaclient-ext
Version: 0.19
Summary: Adds Virtual Interfaces support to python-novaclient
Home-page: https://github.com/rackerlabs/os_virtual_interfacesv2_ext
Author: Rackspace
Author-email: matt.dietz@rackspace.com
License: Apache License, Version 2.0
Platform: UNKNOWN
Classifier: Development Status :: 3 - Alpha
Classifier: Intended Audience :: Developers
Classifier: Intended Audience :: Information Technology
Classifier: License :: OSI Approved :: Apache Software License
Classifier: Operating System :: OS Independent
Classifier: Programming Language :: Python
